{
  "citation": {
    "date": [
      {
        "date": "2024-05-31T13:32:26",
        "dateType": "revision"
      }
    ],
    "description": "No description available.",
    "title": "Global Change Master Directory (GCMD) ISO Topic Categories",
    "edition": "Version 18.7",
    "onlineResource": [
      {
        "uri": "https://gcmd.earthdata.nasa.gov/kms/concept/27fa831b-f131-4f6d-8020-cc4ab0896249?format=json"
      }
    ],
    "identifier": [
      {
        "identifier": "27fa831b-f131-4f6d-8020-cc4ab0896249"
      }
    ]
  },
  "label": "ISO Topic Categories",
  "keywordsUrl": "https://cdn.jsdelivr.net/gh/USGS-NGGDPP/mdEditor-keywords@main/resources/keywords/gcmd-27fa831b-f131-4f6d-8020-cc4ab0896249.json"
}